bgpkit/__init__.py
bgpkit/bgpkit_broker.py
bgpkit/bgpkit_parser.py
bgpkit/bgpkit_roas.py
bgpkit/test_integration.py
pybgpkit-0.6.2.dist-info/licenses/LICENSE
pybgpkit-0.6.2.dist-info/METADATA
pybgpkit-0.6.2.dist-info/WHEEL
pybgpkit-0.6.2.dist-info/top_level.txt
pybgpkit-0.6.2.dist-info/RECORD
