Metadata-Version: 2.4
Name: pybgpkit
Version: 0.6.2
Summary: BGPKIT tools Python bindings
Home-page: https://github.com/bgpkit/pybgpkit
Author: Mingwei Zhang
Author-email: mingwei@bgpkit.com
License-File: LICENSE
Requires-Dist: dataclasses_json
Requires-Dist: pybgpkit-parser==0.6.2
Requires-Dist: requests
Dynamic: author
Dynamic: author-email
Dynamic: description
Dynamic: description-content-type
Dynamic: home-page
Dynamic: license-file
Dynamic: requires-dist
Dynamic: summary
